LICENSE
MANIFEST.in
README.rst
notepad.ico
pynotepad.py
setup.py
pynotepad.egg-info/PKG-INFO
pynotepad.egg-info/SOURCES.txt
pynotepad.egg-info/dependency_links.txt
pynotepad.egg-info/top_level.txt