Metadata-Version: 2.1
Name: pynotepad
Version: 1.3.5
Summary: A featured open-source text editor using tkinter.一款功能齐全的tkinter文本编辑器程序。
Home-page: https://github.com/qfcy/Python/blob/main/pynotepad.pyw
Author: qfcy qq:3076711200
Author-email: 3076711200@qq.com
Keywords: text,editor,notepad,tkinter,pynotepad,文本编辑器
Classifier: Programming Language :: Python
Classifier: Topic :: Text Editors
Classifier: Topic :: Software Development :: User Interfaces
Classifier: Natural Language :: Chinese (Simplified)
Requires: chardet
Requires: windnd
License-File: LICENSE
